{"location": {"callable": {}, "screen": {}, "define": {}, "transform": {}, "label": {"imagemap_example": ["game/tutorial.rpy", 74], "home": ["game/tutorial.rpy", 90], "science": ["game/tutorial.rpy", 82], "start_game": ["game/script.rpy", 67], "start": ["game/script.rpy", 36], "imagemap_done": ["game/tutorial.rpy", 96], "start_tutorial": ["game/tutorial.rpy", 4], "start_testingZone_BACKUP": ["game/testing-zone.rpy", 2], "art": ["game/tutorial.rpy", 86], "start_testingZone": ["game/testing-zone.rpy", 21], "swimming": ["game/tutorial.rpy", 78]}}, "size": [1280, 720], "name": "Time Travel Game V01", "version": "1.0", "error": true}